quantipy/__init__.py
qtypy-0.0.1.dist-info/LICENSE
qtypy-0.0.1.dist-info/METADATA
qtypy-0.0.1.dist-info/WHEEL
qtypy-0.0.1.dist-info/top_level.txt
qtypy-0.0.1.dist-info/RECORD
