Metadata-Version: 2.1
Name: qtypy
Version: 0.0.1
Summary: Make unit conversions obsolete!
Home-page: https://github.com/ahmase/quantipy
License: UNKNOWN
Project-URL: Bug Tracker, https://github.com/ahmase/quantipy/issues
Platform: UNKNOWN
Classifier: Programming Language :: Python :: 3
Classifier: License :: OSI Approved :: BSD License
Classifier: Operating System :: OS Independent
Classifier: Development Status :: 1 - Planning
Requires-Python: >=3.6
License-File: LICENSE
